lyquid/__init__.py
lyquid/liquid_client.py
lyquid-0.0.3.dist-info/LICENSE
lyquid-0.0.3.dist-info/METADATA
lyquid-0.0.3.dist-info/WHEEL
lyquid-0.0.3.dist-info/top_level.txt
lyquid-0.0.3.dist-info/RECORD
