Metadata-Version: 2.1
Name: lyquid
Version: 0.0.3
Summary: Liquid Quoine API client
Home-page: https://github.com/crlqjx/lyquid
Author: Cyril Quijoux
Author-email: 
License: UNKNOWN
Platform: UNKNOWN
Classifier: Programming Language :: Python :: 3
Classifier: License :: OSI Approved :: MIT License
Classifier: Operating System :: OS Independent
Requires-Python: >=3.6
Requires-Dist: requests
Requires-Dist: PyJWT
